[
  {
    "version": "0.6.6",
    "doi": "14201445"
  },
  {
    "version": "0.6.5",
    "doi": "13883175"
  },
  {
    "version": "0.6.4",
    "doi": "11375606"
  },
  {
    "version": "0.6.3",
    "doi": "11063513"
  },
  {
    "version": "0.6.2",
    "doi": "11062735"
  },
  {
    "version": "0.6",
    "doi": "10473004"
  },
  {
    "version": "0.6.0",
    "doi": "10029270"
  },
  {
    "version": "0.5.8",
    "doi": "7939182"
  },
  {
    "version": "0.5.7",
    "doi": "7707348"
  },
  {
    "version": "0.5.6",
    "doi": "7702765"
  },
  {
    "version": "0.5.5",
    "doi": "7672713"
  },
  {
    "version": "0.5.4",
    "doi": "7623342"
  },
  {
    "version": "0.5.3",
    "doi": "7591213"
  },
  {
    "version": "0.5.2",
    "doi": "7559335"
  },
  {
    "version": "0.5.1",
    "doi": "7526893"
  },
  {
    "version": "0.5.0",
    "doi": "7329964"
  },
  {
    "version": "0.4.0",
    "doi": "7023846"
  }
]